skymap_stac/__init__.py
skymap_stac/client.py
skymap_stac/item_search.py
skymap_stac-1.0.7.dist-info/LICENSE
skymap_stac-1.0.7.dist-info/METADATA
skymap_stac-1.0.7.dist-info/WHEEL
skymap_stac-1.0.7.dist-info/top_level.txt
skymap_stac-1.0.7.dist-info/RECORD
