Metadata-Version: 2.1
Name: skymap-stac
Version: 1.0.7
Summary: Skymap STAC package
Author: Hai Anh Do
Author-email: haianhdo193@gmail.com
Keywords: python,stac,skymap,rolodex
Classifier: Programming Language :: Python :: 3
Classifier: Operating System :: MacOS :: MacOS X
Classifier: Operating System :: Microsoft :: Windows
Classifier: Operating System :: Unix
License-File: LICENSE
Requires-Dist: python-dotenv
